{
  "best_global_step": null,
  "best_metric": null,
  "best_model_checkpoint": null,
  "epoch": 8.0,
  "eval_steps": 500,
  "global_step": 208,
  "is_hyper_param_search": false,
  "is_local_process_zero": true,
  "is_world_process_zero": true,
  "log_history": [
    {
      "epoch": 0.19607843137254902,
      "grad_norm": 8.57058048248291,
      "learning_rate": 2e-05,
      "loss": 9.7789,
      "step": 5
    },
    {
      "epoch": 0.39215686274509803,
      "grad_norm": 4.771056175231934,
      "learning_rate": 4.5e-05,
      "loss": 7.4429,
      "step": 10
    },
    {
      "epoch": 0.5882352941176471,
      "grad_norm": 4.175276279449463,
      "learning_rate": 4.898989898989899e-05,
      "loss": 5.8162,
      "step": 15
    },
    {
      "epoch": 0.7843137254901961,
      "grad_norm": 4.372079849243164,
      "learning_rate": 4.772727272727273e-05,
      "loss": 4.6914,
      "step": 20
    },
    {
      "epoch": 0.9803921568627451,
      "grad_norm": 3.252596855163574,
      "learning_rate": 4.6464646464646464e-05,
      "loss": 4.0532,
      "step": 25
    },
    {
      "epoch": 1.156862745098039,
      "grad_norm": 3.6346662044525146,
      "learning_rate": 4.5202020202020204e-05,
      "loss": 3.4746,
      "step": 30
    },
    {
      "epoch": 1.3529411764705883,
      "grad_norm": 2.494567632675171,
      "learning_rate": 4.3939393939393944e-05,
      "loss": 3.3265,
      "step": 35
    },
    {
      "epoch": 1.5490196078431373,
      "grad_norm": 5.708539962768555,
      "learning_rate": 4.267676767676768e-05,
      "loss": 3.0631,
      "step": 40
    },
    {
      "epoch": 1.7450980392156863,
      "grad_norm": 2.739614963531494,
      "learning_rate": 4.141414141414142e-05,
      "loss": 2.7899,
      "step": 45
    },
    {
      "epoch": 1.9411764705882353,
      "grad_norm": 2.4256608486175537,
      "learning_rate": 4.015151515151515e-05,
      "loss": 2.601,
      "step": 50
    },
    {
      "epoch": 2.1176470588235294,
      "grad_norm": 2.8536126613616943,
      "learning_rate": 3.888888888888889e-05,
      "loss": 2.4144,
      "step": 55
    },
    {
      "epoch": 2.313725490196078,
      "grad_norm": 2.010159969329834,
      "learning_rate": 3.7626262626262624e-05,
      "loss": 2.2021,
      "step": 60
    },
    {
      "epoch": 2.5098039215686274,
      "grad_norm": 2.2362794876098633,
      "learning_rate": 3.6363636363636364e-05,
      "loss": 2.1653,
      "step": 65
    },
    {
      "epoch": 2.7058823529411766,
      "grad_norm": 2.1068856716156006,
      "learning_rate": 3.5101010101010104e-05,
      "loss": 2.0371,
      "step": 70
    },
    {
      "epoch": 2.9019607843137254,
      "grad_norm": 2.3155758380889893,
      "learning_rate": 3.3838383838383844e-05,
      "loss": 2.0549,
      "step": 75
    },
    {
      "epoch": 3.0784313725490198,
      "grad_norm": 2.2289607524871826,
      "learning_rate": 3.257575757575758e-05,
      "loss": 1.7718,
      "step": 80
    },
    {
      "epoch": 3.2745098039215685,
      "grad_norm": 2.169297933578491,
      "learning_rate": 3.131313131313132e-05,
      "loss": 1.7405,
      "step": 85
    },
    {
      "epoch": 3.4705882352941178,
      "grad_norm": 2.274463415145874,
      "learning_rate": 3.005050505050505e-05,
      "loss": 1.7975,
      "step": 90
    },
    {
      "epoch": 3.6666666666666665,
      "grad_norm": 1.86915922164917,
      "learning_rate": 2.878787878787879e-05,
      "loss": 1.6433,
      "step": 95
    },
    {
      "epoch": 3.8627450980392157,
      "grad_norm": 1.9040004014968872,
      "learning_rate": 2.7525252525252528e-05,
      "loss": 1.5407,
      "step": 100
    },
    {
      "epoch": 4.03921568627451,
      "grad_norm": 2.1417744159698486,
      "learning_rate": 2.6262626262626268e-05,
      "loss": 1.5763,
      "step": 105
    },
    {
      "epoch": 4.235294117647059,
      "grad_norm": 1.8773130178451538,
      "learning_rate": 2.5e-05,
      "loss": 1.455,
      "step": 110
    },
    {
      "epoch": 4.431372549019608,
      "grad_norm": 1.7762094736099243,
      "learning_rate": 2.3737373737373738e-05,
      "loss": 1.4008,
      "step": 115
    },
    {
      "epoch": 4.627450980392156,
      "grad_norm": 1.7978483438491821,
      "learning_rate": 2.2474747474747475e-05,
      "loss": 1.3176,
      "step": 120
    },
    {
      "epoch": 4.823529411764706,
      "grad_norm": 1.870810866355896,
      "learning_rate": 2.1212121212121215e-05,
      "loss": 1.3232,
      "step": 125
    },
    {
      "epoch": 5.0,
      "grad_norm": 3.9988112449645996,
      "learning_rate": 1.994949494949495e-05,
      "loss": 1.4608,
      "step": 130
    },
    {
      "epoch": 5.196078431372549,
      "grad_norm": 1.8948278427124023,
      "learning_rate": 1.8686868686868688e-05,
      "loss": 1.2793,
      "step": 135
    },
    {
      "epoch": 5.392156862745098,
      "grad_norm": 1.9510754346847534,
      "learning_rate": 1.7424242424242425e-05,
      "loss": 1.2332,
      "step": 140
    },
    {
      "epoch": 5.588235294117647,
      "grad_norm": 1.9799141883850098,
      "learning_rate": 1.6161616161616165e-05,
      "loss": 1.2512,
      "step": 145
    },
    {
      "epoch": 5.784313725490196,
      "grad_norm": 1.8583977222442627,
      "learning_rate": 1.4898989898989898e-05,
      "loss": 1.0645,
      "step": 150
    },
    {
      "epoch": 5.980392156862745,
      "grad_norm": 1.986289620399475,
      "learning_rate": 1.3636363636363637e-05,
      "loss": 1.1984,
      "step": 155
    },
    {
      "epoch": 6.1568627450980395,
      "grad_norm": 1.9377740621566772,
      "learning_rate": 1.2373737373737375e-05,
      "loss": 1.1786,
      "step": 160
    },
    {
      "epoch": 6.352941176470588,
      "grad_norm": 1.6843974590301514,
      "learning_rate": 1.1111111111111112e-05,
      "loss": 1.1036,
      "step": 165
    },
    {
      "epoch": 6.549019607843137,
      "grad_norm": 2.00431227684021,
      "learning_rate": 9.848484848484848e-06,
      "loss": 1.0434,
      "step": 170
    },
    {
      "epoch": 6.745098039215686,
      "grad_norm": 1.722447395324707,
      "learning_rate": 8.585858585858587e-06,
      "loss": 0.9765,
      "step": 175
    },
    {
      "epoch": 6.9411764705882355,
      "grad_norm": 1.9741507768630981,
      "learning_rate": 7.3232323232323234e-06,
      "loss": 1.1384,
      "step": 180
    },
    {
      "epoch": 7.117647058823529,
      "grad_norm": 1.6972185373306274,
      "learning_rate": 6.060606060606061e-06,
      "loss": 1.0928,
      "step": 185
    },
    {
      "epoch": 7.313725490196078,
      "grad_norm": 1.658812165260315,
      "learning_rate": 4.797979797979798e-06,
      "loss": 0.9876,
      "step": 190
    },
    {
      "epoch": 7.509803921568627,
      "grad_norm": 1.9231796264648438,
      "learning_rate": 3.5353535353535352e-06,
      "loss": 1.0456,
      "step": 195
    },
    {
      "epoch": 7.705882352941177,
      "grad_norm": 1.637773871421814,
      "learning_rate": 2.2727272727272728e-06,
      "loss": 0.9828,
      "step": 200
    },
    {
      "epoch": 7.901960784313726,
      "grad_norm": 1.7762556076049805,
      "learning_rate": 1.0101010101010103e-06,
      "loss": 1.0149,
      "step": 205
    }
  ],
  "logging_steps": 5,
  "max_steps": 208,
  "num_input_tokens_seen": 0,
  "num_train_epochs": 8,
  "save_steps": 25,
  "stateful_callbacks": {
    "TrainerControl": {
      "args": {
        "should_epoch_stop": false,
        "should_evaluate": false,
        "should_log": false,
        "should_save": true,
        "should_training_stop": true
      },
      "attributes": {}
    }
  },
  "total_flos": 2637524474265600.0,
  "train_batch_size": 2,
  "trial_name": null,
  "trial_params": null
}
